[
  {
    "id": "INV001",
    "name": "Coffee Beans - House Blend",
    "category": "Beans",
    "unit": "kg",
    "currentStock": 24.5,
    "reorderPoint": 10,
    "idealStock": 30,
    "costPerUnit": 18.99,
    "supplier": "Quality Coffee Suppliers",
    "location": "Main Storage",
    "lastRestocked": "2023-03-10",
    "expiryDate": "2023-09-10"
  },
  {
    "id": "INV002",
    "name": "Coffee Beans - Dark Roast",
    "category": "Beans",
    "unit": "kg",
    "currentStock": 8.2,
    "reorderPoint": 5,
    "idealStock": 15,
    "costPerUnit": 21.50,
    "supplier": "Quality Coffee Suppliers",
    "location": "Main Storage",
    "lastRestocked": "2023-03-01",
    "expiryDate": "2023-09-01"
  },
  {
    "id": "INV003",
    "name": "Whole Milk",
    "category": "Dairy",
    "unit": "L",
    "currentStock": 22,
    "reorderPoint": 10,
    "idealStock": 25,
    "costPerUnit": 2.75,
    "supplier": "Local Dairy Co.",
    "location": "Refrigerator 1",
    "lastRestocked": "2023-03-17",
    "expiryDate": "2023-03-25"
  },
  {
    "id": "INV004",
    "name": "Almond Milk",
    "category": "Dairy Alternatives",
    "unit": "L",
    "currentStock": 5,
    "reorderPoint": 4,
    "idealStock": 12,
    "costPerUnit": 3.50,
    "supplier": "Health Foods Inc.",
    "location": "Refrigerator 2",
    "lastRestocked": "2023-03-15",
    "expiryDate": "2023-04-10"
  },
  {
    "id": "INV005",
    "name": "Vanilla Syrup",
    "category": "Syrups",
    "unit": "bottles",
    "currentStock": 8,
    "reorderPoint": 5,
    "idealStock": 12,
    "costPerUnit": 6.25,
    "supplier": "Flavor Solutions",
    "location": "Syrup Shelf",
    "lastRestocked": "2023-02-20",
    "expiryDate": "2023-08-20"
  },
  {
    "id": "INV006",
    "name": "Caramel Syrup",
    "category": "Syrups",
    "unit": "bottles",
    "currentStock": 3,
    "reorderPoint": 4,
    "idealStock": 10,
    "costPerUnit": 6.25,
    "supplier": "Flavor Solutions",
    "location": "Syrup Shelf",
    "lastRestocked": "2023-02-10",
    "expiryDate": "2023-08-10"
  },
  {
    "id": "INV007",
    "name": "Cup - Small (8oz)",
    "category": "Packaging",
    "unit": "pcs",
    "currentStock": 350,
    "reorderPoint": 200,
    "idealStock": 500,
    "costPerUnit": 0.10,
    "supplier": "Eco Packaging Co.",
    "location": "Supply Closet",
    "lastRestocked": "2023-03-05",
    "expiryDate": null
  },
  {
    "id": "INV008",
    "name": "Cup - Medium (12oz)",
    "category": "Packaging",
    "unit": "pcs",
    "currentStock": 420,
    "reorderPoint": 250,
    "idealStock": 600,
    "costPerUnit": 0.15,
    "supplier": "Eco Packaging Co.",
    "location": "Supply Closet",
    "lastRestocked": "2023-03-05",
    "expiryDate": null
  },
  {
    "id": "INV009",
    "name": "Cup - Large (16oz)",
    "category": "Packaging",
    "unit": "pcs",
    "currentStock": 180,
    "reorderPoint": 150,
    "idealStock": 400,
    "costPerUnit": 0.20,
    "supplier": "Eco Packaging Co.",
    "location": "Supply Closet",
    "lastRestocked": "2023-03-05",
    "expiryDate": null
  },
  {
    "id": "INV010",
    "name": "Lids - Universal",
    "category": "Packaging",
    "unit": "pcs",
    "currentStock": 600,
    "reorderPoint": 300,
    "idealStock": 800,
    "costPerUnit": 0.05,
    "supplier": "Eco Packaging Co.",
    "location": "Supply Closet",
    "lastRestocked": "2023-03-05",
    "expiryDate": null
  },
  {
    "id": "INV011",
    "name": "Sugar Packets",
    "category": "Condiments",
    "unit": "boxes",
    "currentStock": 15,
    "reorderPoint": 5,
    "idealStock": 20,
    "costPerUnit": 8.50,
    "supplier": "Sweet Supplies",
    "location": "Condiment Shelf",
    "lastRestocked": "2023-02-28",
    "expiryDate": "2024-02-28"
  },
  {
    "id": "INV012",
    "name": "Chocolate Powder",
    "category": "Ingredients",
    "unit": "kg",
    "currentStock": 2.2,
    "reorderPoint": 1,
    "idealStock": 3,
    "costPerUnit": 12.75,
    "supplier": "Baking Essentials",
    "location": "Ingredient Shelf",
    "lastRestocked": "2023-03-10",
    "expiryDate": "2023-09-10"
  }
] 